AutoClassifierRegressor/ReportGenerator.py
AutoClassifierRegressor/__init__.py
AutoClassifierRegressor-0.0.6.dist-info/METADATA
AutoClassifierRegressor-0.0.6.dist-info/WHEEL
AutoClassifierRegressor-0.0.6.dist-info/top_level.txt
AutoClassifierRegressor-0.0.6.dist-info/RECORD
