Metadata-Version: 2.1
Name: AutoClassifierRegressor
Version: 0.0.6
Summary: Tools for getting analysis of all classifiers and regressors
Home-page: https://github.com/anagha-bhople/auto_classifier_regressor
Author: Anagha Bhople
Author-email: Anagha Bhople <bhoplea34@gmail.com>, Swapnil Dewalkar <swapnildewalkar1995@gmail.com>
License: MIT License        
Project-URL: Homepage, https://github.com/anagha-bhople/auto_classifier_regressor
Project-URL: Bug Tracker, https://github.com/anagha-bhople/auto_classifier_regressor/issues
Keywords: ML classifier regressor neural network sklearn analysis
Classifier: Programming Language :: Python :: 3
Classifier: License :: OSI Approved :: MIT License
Classifier: Operating System :: OS Independent
Requires-Python: >=3.7
Requires-Dist: pandas
Requires-Dist: numpy
Requires-Dist: sklearn
Requires-Dist: xgboost
Requires-Dist: lightgbm
Requires-Dist: tensorflow
Requires-Dist: keras
Requires-Dist: catboost
Requires-Dist: plotly
Requires-Dist: joblib
